LICENSE
MANIFEST.in
README.rst
onetimepad.py
setup.py
onetimepad.egg-info/PKG-INFO
onetimepad.egg-info/SOURCES.txt
onetimepad.egg-info/dependency_links.txt
onetimepad.egg-info/entry_points.txt
onetimepad.egg-info/top_level.txt