Metadata-Version: 1.1
Name: onetimepad
Version: 1.4
Summary: A hacky implementation of One-time pad
Home-page: http://jailuthra.in/onetimepad
Author: Jai Luthra
Author-email: me@jailuthra.in
License: MIT
Platform: UNKNOWN
Classifier: Development Status :: 3 - Alpha
Classifier: Environment :: Console
Classifier: License :: OSI Approved :: MIT License
Classifier: Operating System :: OS Independent
Classifier: Programming Language :: Python :: 3
Classifier: Topic :: Security :: Cryptography
